{
  "results": [
    {
      "link": "",
      "kinopoisk_id": "1346",
      "date": "1633337859",
      "camrip": "0",
      "ads": "0",
      "block": "",
      "serial": "0",
      "end": "0",
      "quality": "BDRip",
      "translation": "Многоголосый",
      "max_qual": "1080",
      "info": {
        "rus": "По методу Харма",
        "orig": "In Harm's Way",
        "alter": "",
        "year": "1965",
        "country": "США",
        "director": "Отто Преминджер",
        "genre": "драма,военный",
        "actors": "Джон Уэйн,Кирк Дуглас,Патриша Нил,Том Трайон,Пола Прентисс,Брендон Де Уайлд,Джилл Хаворт,Дэна Эндрюс,Стэнли Холлоуэй,Бёрджесс Мередит",
        "description": "1941 год, нападение на военно-морскую базу Перл Харбор японской авиацией явилось началом боевых операций американского флота против японских кораблей в Тихом океане.\r\n\r\nКапитан Рок Торри, преодолевая интриги и карьеризм сослуживцев, вытаскивая из беды друзей и пытаясь наладить отношения с сыном-офицером, становится контр-адмиралом и главнокомандующим рискованной, но необходимой операции «Небесный крюк», которая своим успехом может изменить весь ход войны.\r\n\r\nРискуя своим небольшим флотом, он вступает в неравный бой с японцами и одерживает победу, но ценой жизни друзей и сына.",
        "slogan": "Stripped of everything - they lived and loved and fought as if there were no tomorrow...",
        "premiere": "6 апреля 1965",
        "age": "16",
        "time": "9900",
        "poster": "https://st.kp.yandex.net/images/film_iphone/iphone360_1346.jpg",
        "rating": {
          "rating_kp": "7.066",
          "vote_num_kp": "178",
          "rating_imdb": "7.3",
          "vote_num_imdb": "8542"
        }
      }
    },
    {
      "link": "",
      "kinopoisk_id": "1339535",
      "date": "1633337786",
      "camrip": "0",
      "ads": "1",
      "block": "",
      "serial": "0",
      "end": "0",
      "quality": "WEB-DLRip",
      "translation": "Многоголосый",
      "max_qual": "1080",
      "info": {
        "rus": "Помогите, я уменьшил своих друзей!",
        "orig": "Hilfe, ich hab meine Freunde geschrumpft",
        "alter": "",
        "year": "2021",
        "country": "Германия",
        "director": "Гранц Хенман",
        "genre": "фэнтези,комедия,приключения,семейный",
        "actors": "Оскар Кеймер,Андреа Завацки,Аня Клинг,Аксель Штайн,Джулия Хартманн,Элой Крист,Козима Хенман,Лина Хускер,Михаэль Островский,Тобиаш Шефер",
        "description": "В школе имени Отто Леонарда появилась новенькая ученица, Мелани — милая, веселая, хотя и немного наивная. Девушка сразу приглянулась Феликсу, к большому раздражению Эллы и их компании — им кажется, что именно Мелани причастна к мелким кражам, которые участились в школе после ее появления. Но когда из-за них почти срывается свидание Феликса и Мелани, это становится последней каплей, и подросток решает проучить друзей, уменьшив их в десять раз. Но когда Мелани исчезает вместе с магическим шаром, героям становится не до шуток. Неужели она действительно замешана во всем этом?",
        "slogan": "",
        "premiere": "28 октября 2021",
        "age": "6",
        "time": "5700",
        "poster": "https://st.kp.yandex.net/images/film_iphone/iphone360_1339535.jpg",
        "rating": {
          "rating_kp": "0",
          "vote_num_kp": "51",
          "rating_imdb": "6.5",
          "vote_num_imdb": "18"
        }
      }
    },
    {
      "link": "",
      "kinopoisk_id": "928372",
      "date": "1633331190",
      "camrip": "0",
      "ads": "1",
      "block": "",
      "serial": "1",
      "end": "0",
      "quality": "WEB-DLRip",
      "translation": "ColdFilm",
      "max_qual": "1080",
      "last_season": "5",
      "last_episode": "13",
      "episodes": {
        "4": {
          "1": 720,
          "2": 1080,
          "3": 1080,
          "4": 720,
          "5": 720,
          "6": 1080,
          "7": 1080,
          "8": 1080,
          "9": 720,
          "10": 1080,
          "11": 1080,
          "12": 720,
          "13": 1080
        },
        "5": {
          "1": 1080,
          "2": 1080,
          "3": 1080,
          "4": 1080,
          "5": 1080,
          "6": 1080,
          "7": 1080,
          "8": 1080,
          "9": 1080,
          "10": 1080,
          "11": 1080,
          "12": 1080,
          "13": 1080
        }
      },
      "info": {
        "rus": "По волчьим законам",
        "orig": "Animal Kingdom",
        "alter": "",
        "year": "2016",
        "country": "США",
        "director": "Джон Уэллс, Кристофер Чулак, Дэйв Родригез",
        "genre": "драма,криминал",
        "actors": "Эллен Баркин, Шон Хэтоси, Бен Робсон, Джейк Вири, Финн Коул, Молли Гордон, Каролина Гуерра, Aamya Deva Keroles, Скотт Спидман, Спенсер Трит Кларк",
        "description": "После смерти матери 17-летний Джошуа Коди переезжает к своей родне в пляжный городок в Южной Калифорнии. Семейным делом руководит бабушка Джошуа - Джанин Коди. Главный её помощник - старший из братьев Коди, Поуп. Остальные сыновья тоже помогают матери по мере сил. Вскоре Джошуа понимает, что фамильный бизнес связан с криминалом, и что теперь он волей-неволей сделался частью этого нового для него и смертельно опасного мира.",
        "slogan": "Bad is bred",
        "premiere": "14 июня 2016",
        "age": "0",
        "time": "3600",
        "poster": "https://st.kp.yandex.net/images/film_iphone/iphone360_928372.jpg",
        "rating": {
          "rating_kp": "7.701",
          "vote_num_kp": "5019",
          "rating_imdb": "8.2",
          "vote_num_imdb": "30284"
        }
      }
    },
    {
      "link": "",
      "kinopoisk_id": "1430391",
      "date": "1633323001",
      "camrip": "0",
      "ads": "0",
      "block": "",
      "serial": "0",
      "end": "0",
      "quality": "WEB-DLRip",
      "translation": "Дубляж",
      "max_qual": "1080",
      "info": {
        "rus": "Чего стоит жизнь",
        "orig": "Worth",
        "alter": "",
        "year": "2020",
        "country": "Канада",
        "director": "Veronika Fodor",
        "genre": "драма",
        "actors": "Sara Fowlow,Jayden Baldry,Джессика Нельсон",
        "description": "После теракта 11 сентября 2001 года адвокат Кеннет Фейнберг назначен главной фонда компенсаций жертвам. Он должен буквально оценить стоимость чужих жизней, чтобы выплатить компенсации. Фейнберг оказывается между двух огней — людьми, ждущими возмещения ущерба, который невозможно оценить, и различными лобби, которые стремятся эти компенсации снизить. Кеннет погружается в трагедии тех, кто потерял в башнях своих близких, открывая для себя боль и горе, скрывающиеся за скупыми цифрами на бумаге.",
        "slogan": "",
        "premiere": "",
        "age": "0",
        "time": "7080",
        "poster": "https://m.media-amazon.com/images/M/MV5BZDI4YzBhMzQtM2MzYy00ZGJjLTg2NmItNzJiYTA3OWJjMzUxXkEyXkFqcGdeQXVyMTAyMjQ3NzQ1.jpg",
        "rating": {
          "rating_kp": "0",
          "vote_num_kp": "0",
          "rating_imdb": 0,
          "vote_num_imdb": 0
        }
      }
    },
    {
      "link": "",
      "kinopoisk_id": "972777",
      "date": "1633307575",
      "camrip": "0",
      "ads": "0",
      "block": "",
      "serial": "0",
      "end": "0",
      "quality": "4K UHD",
      "translation": "Дубляж",
      "max_qual": "2160",
      "info": {
        "rus": "Темные времена",
        "orig": "Darkest Hour",
        "alter": "",
        "year": "2017",
        "country": "Великобритания, США",
        "director": "Джо Райт",
        "genre": "история,драма,военный",
        "actors": "Гари Олдман, Кристин Скотт Томас, Бен Мендельсон, Лили Джеймс, Рональд Пикап, Стивен Диллэйн, Николас Джонс, Сэмюэл Уэст, Дэвид Скофилд, Ричард Ламсден",
        "description": "История о первом и решающем шаге Уинстона Черчилля на посту премьер-министра Великобритании, получившего власть при чрезвычайных обстоятельствах. Успехи нацистской армии взбудоражили британское сообщество, но вопреки давлению и страху других политиков Черчилль отказывается идти на соглашение с Гитлером.",
        "slogan": "Никогда не сдавайся",
        "premiere": "1 сентября 2017",
        "age": "16",
        "time": "7500",
        "poster": "https://st.kp.yandex.net/images/film_iphone/iphone360_972777.jpg",
        "rating": {
          "rating_kp": "7.426",
          "vote_num_kp": "41533",
          "rating_imdb": "7.4",
          "vote_num_imdb": "186135"
        }
      }
    },
    {
      "link": "",
      "kinopoisk_id": "741214",
      "date": "1633300960",
      "camrip": "0",
      "ads": "0",
      "block": "",
      "serial": "0",
      "end": "0",
      "quality": "4K WEB-DL",
      "translation": "Дубляж",
      "max_qual": "2160",
      "info": {
        "rus": "Птичий короб",
        "orig": "Bird Box",
        "alter": "",
        "year": "2018",
        "country": "США",
        "director": "Сюзанна Бир",
        "genre": "ужасы,фантастика,драма",
        "actors": "Сандра Буллок, Треванте Роудс, Джон Малкович, Сара Полсон, Джеки Уивер, Роза Салазар, Даниэль Макдональд, Лил Релл, Том Холландер, Машин Ган Келли",
        "description": "Пять лет назад мир погрузился в хаос: увидев нечто, люди кончают жизнь самоубийством. Женщина с двумя пятилетними детьми, услышав по радио о безопасном месте, отправляется на поиски выжившей общины и прихватывает с собой попугаев в коробке. Чтобы сохранить жизнь в этом новом мире, самое главное - не смотреть по сторонам и слушать, как птицы реагируют на приближающуюся опасность.",
        "slogan": "Never Lose Sight of Survival",
        "premiere": "12 ноября 2018",
        "age": "18",
        "time": "7440",
        "poster": "https://st.kp.yandex.net/images/film_iphone/iphone360_741214.jpg",
        "rating": {
          "rating_kp": "6.785",
          "vote_num_kp": "82609",
          "rating_imdb": "6.6",
          "vote_num_imdb": "305231"
        }
      }
    },
    {
      "link": "",
      "kinopoisk_id": "1282491",
      "date": "1633299030",
      "camrip": "0",
      "ads": "1",
      "block": "",
      "serial": "0",
      "end": "0",
      "quality": "WEB-DLRip",
      "translation": "Многоголосый",
      "max_qual": "1080",
      "info": {
        "rus": "Пока мы спим",
        "orig": "While We Sleep",
        "alter": "",
        "year": "2019",
        "country": "США",
        "director": "Анджей Секула",
        "genre": "ужасы",
        "actors": "Брайан Гросс,Джеси Кинг,Оливер Тревена,Pavlo Shpegun,Вячеслав Бабенков,Aleksandr Omelyanov,Дарья Трегубова,Lyra Irene Gross",
        "description": "Нина Иванко смотрит на томографию 13-летней девочки и видит в ней что-то очень знакомое. Когда она пытается понять, что же мешает девочке уснуть, она узнает кое-что очень страшное.",
        "slogan": "Science can&#x27;t explain it",
        "premiere": "",
        "age": "0",
        "time": "5580",
        "poster": "https://thumbs.filmix.tech/posters/0909/orig/poka-my-spim-2019_154532.jpg",
        "rating": {
          "rating_kp": "0",
          "vote_num_kp": "10",
          "rating_imdb": "3.8",
          "vote_num_imdb": "142"
        }
      }
    },
    {
      "link": "",
      "kinopoisk_id": "4308828",
      "date": "1633298452",
      "camrip": "0",
      "ads": "1",
      "block": "",
      "serial": "0",
      "end": "0",
      "quality": "WEB-DLRip",
      "translation": "Многоголосый",
      "max_qual": "480",
      "info": {
        "rus": "Специалист по выживанию",
        "orig": "The Survivalist",
        "alter": "",
        "year": "2021",
        "country": "США",
        "director": "Джон Кейес",
        "genre": "боевик,триллер",
        "actors": "Джонатан Риз Майерс,Джон Малкович,Дженна Ли Грин,Руби Модайн,Джонатан Орсини,Тадеус Стрит,Саймон Филлипс,Чарли Сара,Оби Абили,Tom Pecinka",
        "description": "Прошло полтора года после глобальной эпидемии и практически полным уничтожением цивилизации вызванной смертельно опасным вирусом. Бывшему агенту ФБР приходиться встать на защиту женщины, которая имеет иммунитет к болезни, от главаря банды, устроившего на нее охоту.",
        "slogan": "",
        "premiere": "1 октября 2021",
        "age": "0",
        "time": "5460",
        "poster": "https://m.media-amazon.com/images/M/MV5BZjU5NjM5OTEtNjUzMy00ZDFhLWJhZjQtOGQ1ZTBhYjllZjIzXkEyXkFqcGdeQXVyODk5NjQ4NjE@.jpg",
        "rating": {
          "rating_kp": "0",
          "vote_num_kp": "13",
          "rating_imdb": "3.2",
          "vote_num_imdb": "251"
        }
      }
    },
    {
      "link": "",
      "kinopoisk_id": "4546201",
      "date": "1633298419",
      "camrip": "0",
      "ads": "1",
      "block": "",
      "serial": "0",
      "end": "0",
      "quality": "WEB-DLRip",
      "translation": "Многоголосый",
      "max_qual": "720",
      "info": {
        "rus": "Смертельная гонка",
        "orig": "Wheels of Beauty",
        "alter": "",
        "year": "2021",
        "country": "США",
        "director": "Даг Кэмпбелл",
        "genre": "триллер",
        "actors": "Анджела Николас,Филип Бойд,Шелби Ярдли,Джастин Берти,Alessandra Marandola,Brittany Butler,Девант Уинфри,Michael Houston,Анна Ли,Bentleigh Gleave",
        "description": "Бриттани поступает в гоночную школу. Ее психически неуравновешенный инструктор влюбляется в нее и пытается перtвернуть всю ее жизнь вверх дном.",
        "slogan": "",
        "premiere": "19 сентября 2021",
        "age": "0",
        "time": "5340",
        "poster": "https://m.media-amazon.com/images/M/MV5BNmUwODU5OTctZDJmNy00NzNjLTkzOTQtYTMwY2E5N2FhNzlmXkEyXkFqcGdeQXVyNjU0NTI0Nw@@.jpg",
        "rating": {
          "rating_kp": "0",
          "vote_num_kp": "0",
          "rating_imdb": "4.8",
          "vote_num_imdb": "53"
        }
      }
    },
    {
      "link": "",
      "kinopoisk_id": "1176278",
      "date": "1633298412",
      "camrip": "1",
      "ads": "1",
      "block": "",
      "serial": "0",
      "end": "0",
      "quality": "TS",
      "translation": "Многоголосый",
      "max_qual": "480",
      "info": {
        "rus": "Восемь",
        "orig": "8 (Sekiz)",
        "alter": "",
        "year": "2021",
        "country": "Турция",
        "director": "Bugra Kekik",
        "genre": "боевик",
        "actors": "Мюжде Узман,Hakan Yusufogullari,Реха Озджан,Тургай Танюлкю,Беррин Арисой,Aydan Akboga,Толга Эврен,Суна Селен,Айбике Туран,Cavit Özer",
        "description": "Главные герои фильма пытаются отыскать убийц и всех кто причастен к смерти мальчика, чтобы казнить их.",
        "slogan": "",
        "premiere": "3 сентября 2021",
        "age": "0",
        "time": "5100",
        "poster": "https://thumbs.filmix.tech/posters/2742/orig/vosem-2021_154547.jpg",
        "rating": {
          "rating_kp": "0",
          "vote_num_kp": "7",
          "rating_imdb": 0,
          "vote_num_imdb": 0
        }
      }
    },
    {
      "link": "",
      "kinopoisk_id": "4433838",
      "date": "1633298409",
      "camrip": "0",
      "ads": "0",
      "block": "",
      "serial": "1",
      "end": "1",
      "quality": "WEBRip",
      "translation": "SoftBox",
      "max_qual": "480",
      "last_season": "1",
      "last_episode": "8",
      "episodes": {
        "1": {
          "1": 480,
          "2": 480,
          "3": 480,
          "4": 480,
          "5": 480,
          "6": 480,
          "7": 480,
          "8": 480
        }
      },
      "info": {
        "rus": "Ты даёшь мне силы",
        "orig": "Yu reijeu mi eop",
        "alter": "You Raise Me Up",
        "year": "2021",
        "country": "Корея Южная",
        "director": "Ким Джан-хан",
        "genre": "комедия,мелодрама",
        "actors": "Юн Щи-юн,Ан Хи-ён,Пак Ки-ун,Ким Соль-джин,Чхве Дэ-хун,Киль Хэ-ён,Со Джон-ён,Ли Ган-ук,Ли Но-а,Ли Джи-вон",
        "description": "Готовясь к экзамену на госслужащего, 31-летний мужчина Ён-щик не только набирает лишний вес, но и сталкивается с проблемой пониженного либидо. Не добавляет парню уверенности в себе и тот факт, что урологом оказывается его первая школьная любовь — девушка симпатичная, из обеспеченной семьи, и в добавок с красавцем-бойфрендом.",
        "slogan": "",
        "premiere": "31 августа 2021",
        "age": "0",
        "time": "3600",
        "poster": "https://st.kp.yandex.net/images/film_iphone/iphone360_4433838.jpg",
        "rating": {
          "rating_kp": "0",
          "vote_num_kp": "30",
          "rating_imdb": "7.7",
          "vote_num_imdb": "61"
        }
      }
    },
    {
      "link": "",
      "kinopoisk_id": "1252999",
      "date": "1633297823",
      "camrip": "0",
      "ads": "0",
      "block": "",
      "serial": "0",
      "end": "0",
      "quality": "WEB-DLRip",
      "translation": "Многоголосый",
      "max_qual": "1080",
      "info": {
        "rus": "Бхудж: Гордость Индии",
        "orig": "Bhuj: The Pride of India",
        "alter": "",
        "year": "2021",
        "country": "Индия",
        "director": "Абхишек Дудхайя",
        "genre": "военный,боевик,драма,история",
        "actors": "Пранитха,Аджай Девган,Нора Фатехи,Санджай Датт,Сонакши Синха,Шарад Келкар,Hansa Singh,Ammy Virk,Monazir Khan,Ihana Dhillon",
        "description": "1971 год. История о 300 гуджаратских женщинах, помогавшим ВВС Индии во время войны за независимость Бангладеш.",
        "slogan": "",
        "premiere": "13 августа 2021",
        "age": "0",
        "time": "6780",
        "poster": "https://st.kp.yandex.net/images/film_iphone/iphone360_1252999.jpg",
        "rating": {
          "rating_kp": "0",
          "vote_num_kp": "0",
          "rating_imdb": 0,
          "vote_num_imdb": 0
        }
      }
    },
    {
      "link": "",
      "kinopoisk_id": "1198436",
      "date": "1633297810",
      "camrip": "1",
      "ads": "1",
      "block": "",
      "serial": "0",
      "end": "0",
      "quality": "TS",
      "translation": "Многоголосый",
      "max_qual": "720",
      "info": {
        "rus": "Последствия",
        "orig": "Las consecuencias",
        "alter": "",
        "year": "2021",
        "country": "Нидерланды,Бельгия,Испания",
        "director": "Claudia Pinto",
        "genre": "триллер,драма",
        "actors": "Хуана Акоста,Альфредо Кастро,María Romanillos,Эктор Альтерио,Кармен Элиас,Сония Альмарча,Enrique Gimeno,Christian Checa",
        "description": "Фабиола, 40-летняя женщина, едет на маленький остров, чтобы навестить свою мать. Её интуиция, ей подсказывает, что всё не так, как кажется и что секреты, могут быть связаны с несчастным случаем, которой много лет назад изменил её жизнь.",
        "slogan": "",
        "premiere": "11 июня 2021",
        "age": "0",
        "time": "5760",
        "poster": "https://thumbs.filmix.tech/posters/2127/orig/posledstviya-2021_154541.jpg",
        "rating": {
          "rating_kp": "0",
          "vote_num_kp": "2",
          "rating_imdb": "6.6",
          "vote_num_imdb": "27"
        }
      }
    },
    {
      "link": "",
      "kinopoisk_id": "4523353",
      "date": "1633291846",
      "camrip": "0",
      "ads": "1",
      "block": "",
      "serial": "0",
      "end": "0",
      "quality": "WEB-DLRip",
      "translation": "Многоголосый",
      "max_qual": "1080",
      "info": {
        "rus": "ЛЕГО Звездные войны: Ужасающие истории",
        "orig": "Lego Star Wars Terrifying Tales",
        "alter": "",
        "year": "2021",
        "country": "США",
        "director": "Кен Каннингэм",
        "genre": "мультфильм,ужасы,фантастика,фэнтези,боевик,комедия,приключения,семейный",
        "actors": "Рафаэль Алехандро,Тревор Дивэлл,Джэйк Грин,Тони Хейл,Мэри Элизабет МакГлинн,Мэтт Слоун,Мэтт Слоун,Дэна Снайдер",
        "description": "После событий Star Wars: The Rise of Skywalker По Дэмерон и BB-8 должны совершить аварийную посадку на вулканической планете Мустафар, где они встречаются с жадным и коварным Грабаллой Хаттом. Криминальный авторитет купил замок Дарта Вейдера и превращает его в первый в галактике роскошный отель с системой «все включено», оформленный в стиле ситхов.",
        "slogan": "Disney+",
        "premiere": "1 октября 2021",
        "age": "0",
        "time": "2640",
        "poster": "https://st.kp.yandex.net/images/film_iphone/iphone360_4523353.jpg",
        "rating": {
          "rating_kp": "0",
          "vote_num_kp": "48",
          "rating_imdb": 0,
          "vote_num_imdb": 0
        }
      }
    },
    {
      "link": "",
      "kinopoisk_id": "1321513",
      "date": "1633291831",
      "camrip": "0",
      "ads": "1",
      "block": "",
      "serial": "0",
      "end": "0",
      "quality": "WEB-DLRip",
      "translation": "Многоголосый",
      "max_qual": "1080",
      "info": {
        "rus": "Мэйдей",
        "orig": "Mayday",
        "alter": "",
        "year": "2020",
        "country": "США",
        "director": "Карен Синорр",
        "genre": "драма",
        "actors": "Грэйс Ван Паттен,Миа Гот,Havana Rose Liu,Стефани Соколински,Теодор Пеллерен,Frano Maskovic,Джульетт Льюис,Hyoie O'Grady,Златко Бурич,Nathaniel Allen",
        "description": "У Янека две жены, и он прекрасно маневрирует между ними. Однажды риск того, что кто-то из них узнает о двойных отношениях, резко возрастает, и каждая ложь имеет",
        "slogan": "",
        "premiere": "",
        "age": "0",
        "time": "6840",
        "poster": "https://m.media-amazon.com/images/M/MV5BNGNjZTFmZTQtYTZkYS00ZjM2LWEwYzgtMWJiMjNhYTNjYjNkXkEyXkFqcGdeQXVyMjExMTI5MzU@.jpg",
        "rating": {
          "rating_kp": "0",
          "vote_num_kp": "27",
          "rating_imdb": "4.3",
          "vote_num_imdb": "470"
        }
      }
    },
    {
      "link": "",
      "kinopoisk_id": "4294311",
      "date": "1633291827",
      "camrip": "0",
      "ads": "1",
      "block": "",
      "serial": "0",
      "end": "0",
      "quality": "WEB-DLRip",
      "translation": "Многоголосый",
      "max_qual": "1080",
      "info": {
        "rus": "Поперек горла",
        "orig": "Swallow",
        "alter": "",
        "year": "2021",
        "country": "Великобритания",
        "director": "Джэми Нигл",
        "genre": "короткометражка,комедия",
        "actors": "Charlie Mcconnochie,Sam Cartwright,Xander Phillips,Mark Morriss,Phoebe Ralph,Matt Payne",
        "description": "Нигерия, Лагос, 1980-е. Из-за жизненных трудностей Толани ввязывается в перевозку наркотиков со своей смекалистой подругой и затем сталкивается с последствиями.",
        "slogan": "",
        "premiere": "12 января 2021",
        "age": "0",
        "time": "7680",
        "poster": "https://m.media-amazon.com/images/M/MV5BN2NlODA1NDMtYTcxNS00OTIwLWJjY2YtNmZkMmY2MDY3Y2IxXkEyXkFqcGdeQXVyMTEzMTI1Mjk3.jpg",
        "rating": {
          "rating_kp": "0",
          "vote_num_kp": "0",
          "rating_imdb": 0,
          "vote_num_imdb": 0
        }
      }
    },
    {
      "link": "",
      "kinopoisk_id": "1127642",
      "date": "1633291818",
      "camrip": "0",
      "ads": "1",
      "block": "",
      "serial": "0",
      "end": "0",
      "quality": "WEB-DLRip",
      "translation": "Многоголосый",
      "max_qual": "1080",
      "info": {
        "rus": "Что ломает лёд",
        "orig": "What Breaks the Ice",
        "alter": "",
        "year": "2020",
        "country": "США",
        "director": "Rebecca Eskreis",
        "genre": "драма",
        "actors": "Эйми Маллинз,Мэдлин Клайн,Лукас Гейдж,София Хьюблиц,Кэти Куртин,Шакира Баррера,Бретт Зиммерман,Эрик Дженсен,Джоэль Аллен,Питер Рини",
        "description": "Две девушки из разных миров завязывают глубокую и невероятную дружбу в изнуряющую летнюю жару 1998 года. Их веселые и беззаботные дни быстро заканчиваются, когда они оказываются в центре таинственного убийства.",
        "slogan": "",
        "premiere": "3 октября 2020",
        "age": "0",
        "time": "5940",
        "poster": "https://m.media-amazon.com/images/M/MV5BMzJiMDdmMzEtZGY5NS00NGZmLTgzMGUtYWViN2E5Y2I5OTc4XkEyXkFqcGdeQXVyMTY0ODExMzQ@.jpg",
        "rating": {
          "rating_kp": "0",
          "vote_num_kp": "3",
          "rating_imdb": "4.5",
          "vote_num_imdb": "124"
        }
      }
    },
    {
      "link": "",
      "kinopoisk_id": "4489270",
      "date": "1633286041",
      "camrip": "0",
      "ads": "0",
      "block": "",
      "serial": "0",
      "end": "0",
      "quality": "4K UHD",
      "translation": "Дубляж",
      "max_qual": "2160",
      "info": {
        "rus": "Легенды «Смертельной битвы»: Битва королевств",
        "orig": "Mortal Kombat Legends: Battle of the Realms",
        "alter": "",
        "year": "2021",
        "country": "США",
        "director": "Этан Сполдинг",
        "genre": "мультфильм,фэнтези,боевик,приключения",
        "actors": "Дженнифер Карпентер,Грэй Гриффин,Джоэл МакХэйл,Фред Таташиор,Мэттью Мерсер,Дебра Уилсон,Робин Аткин Даунс,Эмили О’Брайэн,Патрик Сэйтц,Джордан Родригез",
        "description": "Райден с лучшими воинами - Лю Каном, Джонни Кейджем, Соней Блейд и Джаксом возвращаются на Землю, и обнаруживают там армии Внешнего мира. Сам Император Шао Кан предстает перед бойцами, чтобы поставить им очередной ультиматум — или новая Смертельная Битва, или его армии начинают захватывать планету, уничтожая все на своем пути.",
        "slogan": "",
        "premiere": "31 августа 2021",
        "age": "0",
        "time": "5340",
        "poster": "https://st.kp.yandex.net/images/film_iphone/iphone360_4489270.jpg",
        "rating": {
          "rating_kp": "6.556",
          "vote_num_kp": "2330",
          "rating_imdb": 0,
          "vote_num_imdb": 0
        }
      }
    },
    {
      "link": "",
      "kinopoisk_id": "1281911",
      "date": "1633281496",
      "camrip": "0",
      "ads": "1",
      "block": "",
      "serial": "1",
      "end": "0",
      "quality": "WEB-DLRip",
      "translation": "Octopus",
      "max_qual": "1080",
      "last_season": "2",
      "last_episode": "8",
      "episodes": {
        "1": {
          "1": 1080,
          "2": 1080,
          "3": 1080,
          "4": 1080,
          "5": 1080,
          "6": 1080,
          "7": 1080,
          "8": 1080
        },
        "2": {
          "1": 720,
          "2": 720,
          "3": 720,
          "4": 720,
          "5": 720,
          "6": 720,
          "7": 720,
          "8": 720
        }
      },
      "info": {
        "rus": "Любовь 101",
        "orig": "Ask 101",
        "alter": "",
        "year": "2020",
        "country": "Турция",
        "director": "Ахмет Катыксыз,Дениз Иорулмазер",
        "genre": "мелодрама,комедия",
        "actors": "Кубилай Ака,Мерт Языджыоглу,Алина Боз,Селахаттин Пасали,Ипек Филиз Язиджи,Пынар Дениз,Каан Урганджиоглу,Бадэ Ишчил,Мюфит Каяджан,Merve Akkaya",
        "description": "Подростки, проходящие обучение в одном лицее, узнают о том, что их любимая учительница планирует уволиться. Ребята слишком высоко ценят своего преподавателя, поэтому воспринимают эту новость как настоящую трагедию. Не желая мириться с подобным положением дел, школьники из сериала «Любовь 101» начинают думать о том, как отговорить учительницу от ухода.<br /> <br />Вскоре в учебном заведении появляется новенький преподаватель по баскетболу. Молодой учитель сразу же становится популярным среди школьников и своих коллег. Заметив это, ребята понимают, что он может заставить остаться их любимую учительницу. Тогда подростки приступают к разработке грандиозного плана, надеясь свести преподавателей вместе. Если у школьников всё получится, тогда учительница не захочет уходить из учебного заведения и продолжит работу вместе со своим возлюбленным. Этот план кажется ребятам идеальным. <br /> <br />Начав попытки сблизить учителей в первой серии сериала «Любовь 101», подростки даже не представляют, что тёплые и взаимные чувства не появляются по одному лишь щелчку пальцев. Вскоре ребята начнут осознавать, что невозможно спланировать взаимную симпатию и контролировать романтические чувства. ",
        "slogan": "",
        "premiere": "",
        "age": "0",
        "time": "2400",
        "poster": "https://st.kp.yandex.net/images/film_iphone/iphone360_1281911.jpg",
        "rating": {
          "rating_kp": "7.887",
          "vote_num_kp": "1734",
          "rating_imdb": "7.5",
          "vote_num_imdb": "11837"
        }
      }
    },
    {
      "link": "",
      "kinopoisk_id": "1238798",
      "date": "1633278008",
      "camrip": "0",
      "ads": "1",
      "block": "",
      "serial": "0",
      "end": "0",
      "quality": "WEB-DLRip",
      "translation": "Многоголосый",
      "max_qual": "1080",
      "info": {
        "rus": "Имплант",
        "orig": "Implanted",
        "alter": "",
        "year": "2021",
        "country": "США",
        "director": "Fabien Dufils",
        "genre": "фантастика,триллер",
        "actors": "Michelle Girolami,Эдуард Монтут,Кендес МакАдамс,Мартин Эвенс,Бари Химэн,Shirley Huang,Иво Велон,Надер Буссандель,Скотт Бротон,Марк Ресник",
        "description": "Молодая женщина, находясь в тяжелой жизненной ситуации, соглашается на эксперимент, и ей вживляют микрочип с Искусственным Интеллектом. Однако, ей приходится постараться, чтобы выжить, когда ИИ захватывает контроль над ее телом и угрожает убить ее семью.",
        "slogan": "",
        "premiere": "1 ноября 2021",
        "age": "0",
        "time": "5580",
        "poster": "https://m.media-amazon.com/images/M/MV5BOTIwOGU2YWEtMzY2MC00NGExLWJiNzMtMTU2NjU4MTNiZDg3XkEyXkFqcGdeQXVyNDUyMzM5NDc@.jpg",
        "rating": {
          "rating_kp": "0",
          "vote_num_kp": "45",
          "rating_imdb": "6.3",
          "vote_num_imdb": "1260"
        }
      }
    },
    {
      "link": "",
      "kinopoisk_id": "5106",
      "date": "1633273060",
      "camrip": "0",
      "ads": "0",
      "block": "",
      "serial": "0",
      "end": "0",
      "quality": "DVDRip",
      "translation": "Одноголосый",
      "max_qual": "480",
      "info": {
        "rus": "Малыш",
        "orig": "Baby Boy",
        "alter": "",
        "year": "2001",
        "country": "США",
        "director": "Джон Синглтон",
        "genre": "триллер,драма,мелодрама,криминал",
        "actors": "Тайриз Гибсон,Тараджи П. Хенсон,Омар Гудинг,Тамара ЛаШон Басс,Кэнди Энн Браун,Э.Дж. Джонсон,Винг Реймз,Снуп Догг,Энджелл Конвелл,Карим Дж. Граймс",
        "description": "Джоди - молодой чернокожий парень всю жизнь живет под «крылом у мамочки». Он постоянно терзается своей зависимостью, но ничего не собирается менять. У Джоди нет работы, зато есть сын и дочь от двух разных женщин.\r\n\r\nНо, даже несмотря на это, никакая сила не может заставить его покинуть материнское гнездо и начать жить самостоятельно...",
        "slogan": "",
        "premiere": "21 июня 2001",
        "age": "0",
        "time": "7800",
        "poster": "https://st.kp.yandex.net/images/film_iphone/iphone360_5106.jpg",
        "rating": {
          "rating_kp": "6.692",
          "vote_num_kp": "445",
          "rating_imdb": "6.4",
          "vote_num_imdb": "13981"
        }
      }
    },
    {
      "link": "",
      "kinopoisk_id": "1169289",
      "date": "1633266602",
      "camrip": "0",
      "ads": "0",
      "block": "",
      "serial": "0",
      "end": "0",
      "quality": "WEB-DLRip",
      "translation": "Многоголосый",
      "max_qual": "1080",
      "info": {
        "rus": "Дива",
        "orig": "Diba",
        "alter": "",
        "year": "2020",
        "country": "Корея Южная",
        "director": "Чо Сыр-е",
        "genre": "триллер,детектив",
        "actors": "Щин Мин-а,Ли Ю-ён,Ли Гю-хён,О Ха-ни,Чу Сок-тхэ,Чи И-су,Юнгым Сон-а,Хо Дон-вон,Пэ Со-ён",
        "description": "Знаменитую чемпионку по прыжкам в воду постигает несчастный случай, в результате которого женщина теряет память, а так же бесследно исчезает её лучшая подруга и напарница. Попытки вспомнить прошлое открывают неприятную правду.",
        "slogan": "",
        "premiere": "23 сентября 2020",
        "age": "0",
        "time": "5040",
        "poster": "https://st.kp.yandex.net/images/film_iphone/iphone360_1169289.jpg",
        "rating": {
          "rating_kp": "0",
          "vote_num_kp": "89",
          "rating_imdb": "5.4",
          "vote_num_imdb": "146"
        }
      }
    },
    {
      "link": "",
      "kinopoisk_id": "508161",
      "date": "1633266022",
      "camrip": "0",
      "ads": "1",
      "block": "",
      "serial": "1",
      "end": "0",
      "quality": "BDRip",
      "translation": "ColdFilm",
      "max_qual": "1080",
      "last_season": "11",
      "last_episode": "8",
      "episodes": {
        "9": {
          "1": 720,
          "2": 720,
          "3": 720,
          "4": 720,
          "5": 720,
          "6": 720,
          "7": 720,
          "8": 720
        },
        "10": {
          "1": 1080,
          "2": 1080,
          "3": 720,
          "4": 1080,
          "5": 720,
          "6": 720,
          "7": 1080,
          "8": 1080,
          "9": 1080,
          "10": 1080,
          "11": 1080,
          "12": 1080,
          "13": 1080,
          "14": 1080,
          "15": 1080,
          "16": 1080,
          "17": 1080,
          "18": 1080,
          "19": 1080,
          "20": 1080,
          "21": 1080,
          "22": 1080
        },
        "11": {
          "1": 1080,
          "2": 1080,
          "3": 1080,
          "4": 1080,
          "5": 1080,
          "6": 1080,
          "7": 1080,
          "8": 1080
        }
      },
      "info": {
        "rus": "Ходячие мертвецы",
        "orig": "The Walking Dead",
        "alter": "",
        "year": "2010",
        "country": "США",
        "director": "Грег Никотеро, Майкл Е. Сатраземис, Эрнест Р. Дикерсон",
        "genre": "ужасы,фантастика,триллер,драма",
        "actors": "Норман Ридус, Мелисса Сюзанн МакБрайд, Эндрю Линкольн, Лорен Кохэн, Данай Гурира, Чендлер Риггз, Аланна Мастерсон, Джош МакДермитт, Кристиан Серратос, Стивен Ян",
        "description": "Сериал рассказывает историю жизни семьи шерифа после того, как «зомби» - эпидемия апокалиптических масштабов захлестнула земной шар. Шериф Рик Граймс путешествует со своей семьей и небольшой группой выживших в поисках безопасного места для жизни. Но постоянный страх смерти каждый день приносит тяжелые потери, заставляя героев почувствовать глубины человеческой жестокости. Рик пытается спасти свою семью, и открывает для себя, что всепоглощающий страх тех, кто выжил, может быть опаснее бессмысленных мертвецов, бродящих по земле.",
        "slogan": "Fight the dead. Fear the living",
        "premiere": "4 ноября 2010",
        "age": "18",
        "time": "2580",
        "poster": "https://st.kp.yandex.net/images/film_iphone/iphone360_508161.jpg",
        "rating": {
          "rating_kp": "7.992",
          "vote_num_kp": "325514",
          "rating_imdb": "8.2",
          "vote_num_imdb": "905237"
        }
      }
    },
    {
      "link": "",
      "kinopoisk_id": "4526511",
      "date": "1633264895",
      "camrip": "0",
      "ads": "0",
      "block": "",
      "serial": "0",
      "end": "0",
      "quality": "WEB-DLRip",
      "translation": "Двухголосый",
      "max_qual": "1080",
      "info": {
        "rus": "Синева",
        "orig": "Blue",
        "alter": "",
        "year": "2021",
        "country": "Япония",
        "director": "Кэисукэ Ёсида",
        "genre": "драма,спорт",
        "actors": "Кэнъити Мацуяма,Фумино Кимура,Токио Эмото,Масахиро Хигасидэ,Даисукэ Мацуки,Синитиро Мацуура,Пистол Такэхара,Аюри Ёсинага",
        "description": "Боксер Нобуто Урита много тренируется, но, как бы он не старался, он проигрывает все бои. В одном зале с ним занимается Кадзуки Огава, у него дела идут хорошо, и скоро он наверняка станет чемпионом. А еще Кадзуки помолвлен с Тикой Амано, первой любовью Нобуто.",
        "slogan": "",
        "premiere": "9 апреля 2021",
        "age": "0",
        "time": "6420",
        "poster": "https://st.kp.yandex.net/images/film_iphone/iphone360_4526511.jpg",
        "rating": {
          "rating_kp": "0",
          "vote_num_kp": "11",
          "rating_imdb": "6.5",
          "vote_num_imdb": "68"
        }
      }
    },
    {
      "link": "",
      "kinopoisk_id": "885615",
      "date": "1633260991",
      "camrip": "0",
      "ads": "0",
      "block": "",
      "serial": "0",
      "end": "0",
      "quality": "WEB-DLRip",
      "translation": "Дубляж",
      "max_qual": "1080",
      "info": {
        "rus": "Медведи Буни: Таинственная зима",
        "orig": "Boonie Bears: Mystical Winter",
        "alter": "",
        "year": "2015",
        "country": "Китай",
        "director": "Дин Лян,Лю Фуюань",
        "genre": "мультфильм,комедия,приключения",
        "actors": "Мэн Юйтянь,Сунь Яодун,Чжан Бинцзюнь",
        "description": "В лесу бушует невиданная снежная буря, когда на Сосновой горе неожиданно появляется загадочное существо. Вслед за ним прибывают несколько незнакомцев, которые устраивают настоящий переполох, пытаясь поймать сказочного монстра. Они уверены, что непонятный зверь собирается уничтожить Сосновую гору.",
        "slogan": "",
        "premiere": "11 февраля 2016",
        "age": "6",
        "time": "5340",
        "poster": "https://st.kp.yandex.net/images/film_iphone/iphone360_885615.jpg",
        "rating": {
          "rating_kp": "4.677",
          "vote_num_kp": "568",
          "rating_imdb": "5.6",
          "vote_num_imdb": "126"
        }
      }
    },
    {
      "link": "",
      "kinopoisk_id": "4362629",
      "date": "1633258802",
      "camrip": "0",
      "ads": "0",
      "block": "",
      "serial": "0",
      "end": "0",
      "quality": "WEB-DLRip",
      "translation": "Многоголосый",
      "max_qual": "1080",
      "info": {
        "rus": "Безумное кино для взрослых",
        "orig": "Babardeala cu bucluc sau porno balamuc",
        "alter": "Неудачный трах, или Безумное порно",
        "year": "2021",
        "country": "Румыния,Хорватия,Чехия,Люксембург",
        "director": "Раду Жуде",
        "genre": "драма,комедия",
        "actors": "Катя Паскарю,Клаудия Иеремия,Олимпия Малаи,Никодим Унгуряну,Александру Поточан,Анди Васлуяну,Габриел Спахиу,Флорин Петреску,Alex Bogdan,Кристина Чепрага",
        "description": "Эми — школьная учительница, чья карьера и репутация оказываются под угрозой, когда в интернет попадает интимное видео с ее участием. Возмущенные до глубины души родители требуют ее немедленного увольнения. Но Эми не собирается так легко сдаваться.",
        "slogan": "",
        "premiere": "2 марта 2021",
        "age": "18",
        "time": "6360",
        "poster": "https://st.kp.yandex.net/images/film_iphone/iphone360_4362629.jpg",
        "rating": {
          "rating_kp": "6.198",
          "vote_num_kp": "6570",
          "rating_imdb": "6.8",
          "vote_num_imdb": "2406"
        }
      }
    },
    {
      "link": "",
      "kinopoisk_id": "1271089",
      "date": "1633257683",
      "camrip": "0",
      "ads": "1",
      "block": "",
      "serial": "0",
      "end": "0",
      "quality": "WEB-DLRip",
      "translation": "Многоголосый",
      "max_qual": "720",
      "info": {
        "rus": "Девушки старого города",
        "orig": "Tu zi bao li",
        "alter": "",
        "year": "2020",
        "country": "Китай",
        "director": "Шэнь Юй",
        "genre": "драма,криминал",
        "actors": "Джо Чэнь,Реджина Вань,Хуан Цзюэ,Ли Гэнси,Пань Биньлун,An Shi",
        "description": "В жизни 17-летней школьницы внезапно возникает биологическая мать, которая оставила её ещё ребенком. Вместо того чтобы возненавидеть её, девушка вдруг начинает фантазировать о той беззаботной жизни, которой якобы живет её мать. Реальность же оказывается гораздо прозаичнее.",
        "slogan": "",
        "premiere": "1 ноября 2020",
        "age": "0",
        "time": "6360",
        "poster": "https://st.kp.yandex.net/images/film_iphone/iphone360_1271089.jpg",
        "rating": {
          "rating_kp": "0",
          "vote_num_kp": "5",
          "rating_imdb": 0,
          "vote_num_imdb": 0
        }
      }
    },
    {
      "link": "",
      "kinopoisk_id": "1221530",
      "date": "1633255569",
      "camrip": "0",
      "ads": "0",
      "block": "",
      "serial": "1",
      "end": "0",
      "quality": "WEB-DLRip",
      "translation": "Кравец",
      "max_qual": "1080",
      "last_season": "2",
      "last_episode": "6",
      "episodes": {
        "1": {
          "1": 1080,
          "2": 1080,
          "3": 1080,
          "4": 1080,
          "5": 1080,
          "6": 1080
        },
        "2": {
          "1": 1080,
          "2": 1080,
          "3": 1080,
          "4": 1080,
          "5": 1080,
          "6": 1080
        }
      },
      "info": {
        "rus": "Ошибка 404",
        "orig": "Code 404",
        "alter": "",
        "year": "2020",
        "country": "Великобритания",
        "director": "Аль Кэмпбелл",
        "genre": "фантастика,боевик,триллер,комедия,криминал",
        "actors": "Стивен Грэм,Дэниэл Мейс,Рози Кавальеро,Аманда Пэйтон,Саймон Стратт,Анна Максвелл Мартин,Мишель Гринидж,Эмили Ллойд-Сайни,Стив Орам,Ричард Гэдд",
        "description": "Детектив-инспектор Джон гибнет на задании. В его лице правосудие теряет блестящего бойца, однако тело мужчины попадает в экспериментальную программу, где ему внедряют искусственный интеллект и возвращают из царства мертвых. Но есть один нюанс: «новый» Джон, кажется, растерял львиную долю профессиональных навыков.",
        "slogan": "",
        "premiere": "30 апреля 2020",
        "age": "18",
        "time": "1500",
        "poster": "https://st.kp.yandex.net/images/film_iphone/iphone360_1221530.jpg",
        "rating": {
          "rating_kp": "6.404",
          "vote_num_kp": "970",
          "rating_imdb": "6.3",
          "vote_num_imdb": "1707"
        }
      }
    },
    {
      "link": "",
      "kinopoisk_id": "7424",
      "date": "1633252252",
      "camrip": "0",
      "ads": "0",
      "block": "",
      "serial": "0",
      "end": "0",
      "quality": "DVDRip",
      "translation": "Двухголосый",
      "max_qual": "480",
      "info": {
        "rus": "Среди друзей",
        "orig": "Amongst Friends",
        "alter": "",
        "year": "1993",
        "country": "США",
        "director": "Роб Уайсс",
        "genre": "драма,криминал",
        "actors": "Крис Сантос,Майкл Леб,Кристиан Том,Лу Кантельмо,Джерри Леонард,Дэвид Степкин,Грег Бернарди,Лу Бернарди,Чарльз Маттина,Адам Монтальбано",
        "description": "Медленное погружение в начало 70-х годов, в мир воспоминаний главного героя, в среду городских подростков, в атмосферу криминальных интересов, на грань опасности, которая невидима, как радиация, и непознаваема, как любовь. Опасность для жизни можно только ощутить нутром, и главное — не опоздать...",
        "slogan": "When Crime is a Way of Life, You Never Know if You&#x27;re Amongst Enemies...or Amongst Friends",
        "premiere": "23 января 1993",
        "age": "16",
        "time": "5160",
        "poster": "https://st.kp.yandex.net/images/film_iphone/iphone360_7424.jpg",
        "rating": {
          "rating_kp": "5.423",
          "vote_num_kp": "61",
          "rating_imdb": "5.6",
          "vote_num_imdb": "592"
        }
      }
    },
    {
      "link": "",
      "kinopoisk_id": "160922",
      "date": "1633252203",
      "camrip": "0",
      "ads": "0",
      "block": "",
      "serial": "0",
      "end": "0",
      "quality": "DVDRip",
      "translation": "Многоголосый",
      "max_qual": "480",
      "info": {
        "rus": "Боги речного мира",
        "orig": "Riverworld",
        "alter": "",
        "year": "2003",
        "country": "Канада,Новая Зеландия,Великобритания,США",
        "director": "Кари Скогланд",
        "genre": "фантастика,фэнтези",
        "actors": "Брэд Джонсон,Карен Холнесс,Эмили Ллойд,Джереми Бирчал,Кевин Смит,Никита Кирсли,Брайан Мур,Кемерон Дейдду,Джонатан Кэйк,Паоло Ротондо",
        "description": "Джефф Хэйл - американский астронавт, был на высокой орбите Земли, когда его настигла смерть... очнулся он под водой, в неком подобии воздушного пузыря, из которого ему помог выбраться призрачного вида незнакомец, с закрывающим лицо капюшоном.",
        "slogan": "",
        "premiere": "22 марта 2003",
        "age": "16",
        "time": "5160",
        "poster": "https://st.kp.yandex.net/images/film_iphone/iphone360_160922.jpg",
        "rating": {
          "rating_kp": "5.587",
          "vote_num_kp": "550",
          "rating_imdb": "5.2",
          "vote_num_imdb": "2435"
        }
      }
    },
    {
      "link": "",
      "kinopoisk_id": "4554029",
      "date": "1633252055",
      "camrip": "0",
      "ads": "0",
      "block": "",
      "serial": "1",
      "end": "0",
      "quality": "WEB-DLRip",
      "translation": "Оригинал",
      "max_qual": "1080",
      "last_season": "1",
      "last_episode": "12",
      "episodes": {
        "1": {
          "1": 1080,
          "2": 1080,
          "3": 1080,
          "4": 1080,
          "5": 1080,
          "6": 1080,
          "7": 1080,
          "8": 1080,
          "9": 1080,
          "10": 1080,
          "11": 1080,
          "12": 1080
        }
      },
      "info": {
        "rus": "Команда Флоры",
        "orig": "Команда Флоры",
        "alter": "",
        "year": "2021",
        "country": "Россия",
        "director": "Иван Пшонкин,Алексей Котеночкин",
        "genre": "детский,комедия,приключения",
        "actors": "Лариса Брохман, Лина Иванова, Анна Штукатурова",
        "description": "История о захватывающих приключениях девочки Флоры и пятерых ее друзей — антропоморфных чудо-растений. Получив сигнал Зеленой Тревоги, дружная Команда Флоры спешит на помощь Природе, пользуясь удивительными способностями каждого чудо-растения, а также знаниями, изобретениями и находчивостью Флоры.",
        "slogan": "",
        "premiere": "",
        "age": "0",
        "time": "660",
        "poster": "https://st.kp.yandex.net/images/film_iphone/iphone360_4554029.jpg",
        "rating": {
          "rating_kp": "0",
          "vote_num_kp": "0",
          "rating_imdb": 0,
          "vote_num_imdb": 0
        }
      }
    },
    {
      "link": "",
      "kinopoisk_id": "1202423",
      "date": "1633251937",
      "camrip": "0",
      "ads": "0",
      "block": "",
      "serial": "1",
      "end": "0",
      "quality": "WEB-DLRip",
      "translation": "Zone Vision",
      "max_qual": "1080",
      "last_season": "2",
      "last_episode": "1",
      "episodes": {
        "1": {
          "1": 1080,
          "2": 1080,
          "3": 1080,
          "4": 1080,
          "5": 1080,
          "6": 1080,
          "7": 1080,
          "8": 1080,
          "9": 1080,
          "10": 1080,
          "11": 1080
        },
        "2": {
          "1": 1080
        }
      },
      "info": {
        "rus": "Великий Север",
        "orig": "The Great North",
        "alter": "",
        "year": "2021",
        "country": "США",
        "director": "Тони Дженнаро,Уилл Строуд,Нил Граф",
        "genre": "мультфильм,комедия",
        "actors": "Ник Офферман,Дженни Слейт,Уилл Форте,Дульсе Слоун,Пол Руст,Апарна Нанчерла,Меган Маллалли,Аланис Мориссетт,Дэвид Херман,Брук Диллман",
        "description": "О приключениях отца-одиночки и его странной семьи в холодных землях Аляски.",
        "slogan": "It&#x27;s great up here",
        "premiere": "3 января 2021",
        "age": "16",
        "time": "1320",
        "poster": "https://st.kp.yandex.net/images/film_iphone/iphone360_1202423.jpg",
        "rating": {
          "rating_kp": "7.178",
          "vote_num_kp": "2803",
          "rating_imdb": "6.5",
          "vote_num_imdb": "2248"
        }
      }
    },
    {
      "link": "",
      "kinopoisk_id": "1049207",
      "date": "1633251609",
      "camrip": "0",
      "ads": "0",
      "block": "",
      "serial": "1",
      "end": "0",
      "quality": "HDTVRip",
      "translation": "AniLibria",
      "max_qual": "1080",
      "last_season": "2",
      "last_episode": "1",
      "episodes": {
        "1": {
          "1": 720,
          "2": 720,
          "3": 720,
          "4": 720,
          "5": 720,
          "6": 720,
          "7": 720,
          "8": 720,
          "9": 720,
          "10": 720,
          "11": 720,
          "12": 720
        },
        "2": {
          "1": 1080
        }
      },
      "info": {
        "rus": "Кафе из другого мира",
        "orig": "Isekai Shokudô",
        "alter": "Isekai Shokudou / Ресторанчик из иного мира / Restaurant to Another World",
        "year": "2017",
        "country": "Япония",
        "director": "Масато Дзимбо",
        "genre": "аниме,мультфильм,фантастика,фэнтези,комедия",
        "actors": "Кадзухико Иноуэ,Кикуко Иноуэ,Кэиити Сано,Такао Сано,Кристофер Сабат,Моника Риал,Кэйтлин Гласс,Стефани Янг,Чарльз Кэмпбелл,Дженни Тирадо",
        "description": "На первый взгляд «Нэкоя» – это самое обычное кафе, но по субботам заведение открывает двери в другой мир, населенный эльфами, драконами, людьми-животными и прочими фантастическими существами.",
        "slogan": "",
        "premiere": "3 июля 2017",
        "age": "0",
        "time": "1380",
        "poster": "https://st.kp.yandex.net/images/film_iphone/iphone360_1049207.jpg",
        "rating": {
          "rating_kp": "7.289",
          "vote_num_kp": "1562",
          "rating_imdb": "7.2",
          "vote_num_imdb": "353"
        }
      }
    },
    {
      "link": "",
      "kinopoisk_id": "1229579",
      "date": "1633251440",
      "camrip": "0",
      "ads": "0",
      "block": "",
      "serial": "1",
      "end": "0",
      "quality": "WEB-DLRip",
      "translation": "Дубляж",
      "max_qual": "1080",
      "last_season": "2",
      "last_episode": "6",
      "episodes": {
        "1": {
          "1": 1080,
          "2": 1080,
          "3": 1080,
          "4": 1080,
          "5": 1080,
          "6": 1080
        },
        "2": {
          "1": 1080,
          "2": 1080,
          "3": 1080,
          "4": 1080,
          "5": 1080,
          "6": 1080
        }
      },
      "info": {
        "rus": "Выход есть",
        "orig": "Exit",
        "alter": "",
        "year": "2019",
        "country": "Норвегия",
        "director": "Эйстейн Карлсен",
        "genre": "драма",
        "actors": "Саймон Дж. Бергер,Агнес Киттелсен,Пол Сверре Валхейм Хаген,Тобиас Зантельман,Йон Эйгарден,Катарина Ву,Ине Марие Вильман,Эллен Хелиндер,Рольф Лассгорд,Caroline Myrbråten",
        "description": "Невероятного богатства подчас недостаточно, чтобы побороть скуку и заполнить пустоту в душе. Четверо друзей, короли финансовой элиты, нашли свой выход: секс, наркотики и насилие. Смогут ли они остановиться на этом опасном пути, прежде чем погубят себя и свои семьи?",
        "slogan": "",
        "premiere": "1 июня 2019",
        "age": "0",
        "time": "1800",
        "poster": "https://st.kp.yandex.net/images/film_iphone/iphone360_1229579.jpg",
        "rating": {
          "rating_kp": "7.583",
          "vote_num_kp": "345",
          "rating_imdb": "8.2",
          "vote_num_imdb": "8308"
        }
      }
    },
    {
      "link": "",
      "kinopoisk_id": "1064020",
      "date": "1633251066",
      "camrip": "0",
      "ads": "1",
      "block": "",
      "serial": "0",
      "end": "0",
      "quality": "WEB-DLRip",
      "translation": "Многоголосый",
      "max_qual": "1080",
      "info": {
        "rus": "Сорвать куш",
        "orig": "Hustle Down",
        "alter": "",
        "year": "2021",
        "country": "США",
        "director": "Р. Эллис Фрэзиер",
        "genre": "боевик",
        "actors": "Том Сайзмор,Амар Сидху,Бай Лин,Кевин Гейдж,Рэймонд Дж. Бэрри,Ванесса Энджел,Ноэль Гульеми,Дэвид Фернандез,Victorya Brandart,Луис Гатика",
        "description": "Калли, мелкий мошенник и водитель наркокартеля Баха, полагается на опытного охотника за головами поневоле Тёрка, чтобы держаться подальше от безжалостного убийцы и злобных головорезов во главе с лидером конкурирующей банды после того, как Калли угнал машину с наличными, предназначенными для его босса. Вместе они встречают Кристал, страстную танцовщицу с кучей секретов и ещё большей заинтересованностью во всём этом, чем они ожидали. Если Калли убедит Тёрка согласиться на его безумный план, он сможет вернуться к бывшей жене и дочери живым.",
        "slogan": "",
        "premiere": "",
        "age": "0",
        "time": "5940",
        "poster": "https://thumbs.filmix.tech/posters/2756/orig/sorvat-kush-2021_154517.jpg",
        "rating": {
          "rating_kp": "0",
          "vote_num_kp": "0",
          "rating_imdb": 0,
          "vote_num_imdb": 0
        }
      }
    },
    {
      "link": "",
      "kinopoisk_id": "1095999",
      "date": "1633251002",
      "camrip": "0",
      "ads": "1",
      "block": "",
      "serial": "0",
      "end": "0",
      "quality": "WEB-DLRip",
      "translation": "Многоголосый",
      "max_qual": "720",
      "info": {
        "rus": "Как стать знаменитым за 7 дней",
        "orig": "Famosi in 7 giorni",
        "alter": "",
        "year": "2019",
        "country": "Италия",
        "director": "Джанлука Ваннуччи",
        "genre": "комедия",
        "actors": "Veronica Bitto,Андреа Ронкато,Стефано Френьи,Лучиано Миле,Вероника Урбан,Элеонора Болла,Andrea Porti,Антонио Кортезе,Джанлука Ваннуччи,Max Giusti",
        "description": "Четыре обнадеживающих актера решают записаться на курсы актерского мастерства, которые могли бы обеспечить им роль в крупном режиссерском фильме. Однако курс обнаруживает мошенничество. Четверо актеров не любят, когда их обманывают. Найдя автора аферы, они без промедления воспользуются дурными манерами, чтобы вернуть деньги. Как только они получают свои деньги, известный вымышленный актер советует им использовать их для получения роли в важном режиссерском фильме. Но это просто очередная афера. Месть четверки на этот раз будет ужасной и сделает их знаменитыми.",
        "slogan": "",
        "premiere": "",
        "age": "0",
        "time": "4920",
        "poster": "https://thumbs.filmix.tech/posters/2857/orig/kak-stat-znamenitym-za-7-dney-2019_154518.jpg",
        "rating": {
          "rating_kp": "0",
          "vote_num_kp": "0",
          "rating_imdb": 0,
          "vote_num_imdb": 0
        }
      }
    },
    {
      "link": "",
      "kinopoisk_id": "4470133",
      "date": "1633250929",
      "camrip": "0",
      "ads": "1",
      "block": "",
      "serial": "0",
      "end": "0",
      "quality": "WEB-DLRip",
      "translation": "Многоголосый",
      "max_qual": "1080",
      "info": {
        "rus": "Эвакуация",
        "orig": "Recovery",
        "alter": "Stop and Go",
        "year": "2021",
        "country": "США",
        "director": "Мэллори Эвертон,Стивен Мик",
        "genre": "комедия,драма",
        "actors": "Уитни Колл,Мэллори Эвертон,Джулия Джолли,Энн Сворд Хансен,Стивен Мик,Джессика Дролет,Бэйли Торнок,Ной Кершисник,Дора Макдональд,Тайлер Эндрю Джонс",
        "description": "Mарт 2020 года. Только что купив теперь бесполезные акции авиакомпаний и отелей, Джейми отправляется с сестрой в самое важное путешествие своей жизни — безумную поездку через всю Америку в разгар пандемии — чтобы вызволить свою бабушку из дома престарелых.",
        "slogan": "",
        "premiere": "21 октября 2021",
        "age": "0",
        "time": "4800",
        "poster": "https://st.kp.yandex.net/images/film_iphone/iphone360_4470133.jpg",
        "rating": {
          "rating_kp": "0",
          "vote_num_kp": "25",
          "rating_imdb": "5.3",
          "vote_num_imdb": "165"
        }
      }
    },
    {
      "link": "",
      "kinopoisk_id": "1165837",
      "date": "1633250869",
      "camrip": "0",
      "ads": "1",
      "block": "",
      "serial": "0",
      "end": "0",
      "quality": "WEB-DLRip",
      "translation": "Многоголосый",
      "max_qual": "1080",
      "info": {
        "rus": "Певица на всю голову",
        "orig": "Falling for Figaro",
        "alter": "",
        "year": "2020",
        "country": "Австралия,США,Великобритания",
        "director": "Бен Луин",
        "genre": "мелодрама,комедия",
        "actors": "Гари Льюис,Даниэль Макдональд,Джоанна Ламли,Шазад Латиф,Хью Скиннер,Ребекка Бенсон,Йен Ханмор,Bhav Joshi,Christina Bennington,Saskia Ashdown",
        "description": "Блестящая молодая девушка - менеджер фонда оставляет свою работу, которая не приносит ей удовольствия, и давнего бойфренда, чтобы отправиться вслед за мечтой всей своей жизни и стать оперной певицей в Шотландском нагорье.",
        "slogan": "",
        "premiere": "17 февраля 2022",
        "age": "0",
        "time": "6240",
        "poster": "https://m.media-amazon.com/images/M/MV5BZGRiYTM2NDItMGRlMS00ZmM5LWEwMGYtMTE2MDMwM2ZjOWU4XkEyXkFqcGdeQXVyMTg1MzYyMzQ@.jpg",
        "rating": {
          "rating_kp": "0",
          "vote_num_kp": "15",
          "rating_imdb": "6.2",
          "vote_num_imdb": "224"
        }
      }
    },
    {
      "link": "",
      "kinopoisk_id": "1391142",
      "date": "1633250776",
      "camrip": "0",
      "ads": "1",
      "block": "",
      "serial": "0",
      "end": "0",
      "quality": "WEB-DLRip",
      "translation": "Многоголосый",
      "max_qual": "1080",
      "info": {
        "rus": "Последний оставшийся в живых",
        "orig": "Last Man Down",
        "alter": "",
        "year": "2021",
        "country": "Швеция,Великобритания",
        "director": "Fansu Njie",
        "genre": "боевик",
        "actors": "Дэниэл Стисен,Ольга Кент,Дэниэл Неме,Станислав Яневский,Мадлен Волл,Наташа Мальте,Stephanie Siadatan,Роберт Фоллин,Майкл Билингтон,Pasi Antero Remsu",
        "description": "Бескомпромиссный вояка с ментальностью героев ушедшей эпохи, Джон Вуд оставил позади осколки разрушенной цивилизации, чтобы вернуться к своим корням в лесу, после того как мир поразила пандемия вируса.",
        "slogan": "",
        "premiere": "",
        "age": "0",
        "time": "5280",
        "poster": "https://thumbs.filmix.tech/posters/2754/orig/posledniy-ostavshiysyanbspv-zhivyh-2021_154508.jpg",
        "rating": {
          "rating_kp": "0",
          "vote_num_kp": "44",
          "rating_imdb": 0,
          "vote_num_imdb": 0
        }
      }
    },
    {
      "link": "",
      "kinopoisk_id": "838222",
      "date": "1633248370",
      "camrip": "0",
      "ads": "0",
      "block": "",
      "serial": "0",
      "end": "0",
      "quality": "BDRip",
      "translation": "Многоголосый",
      "max_qual": "1080",
      "info": {
        "rus": "Идеальный день, чтобы умереть",
        "orig": "A Perfect Day",
        "alter": "",
        "year": "2015",
        "country": "Испания",
        "director": "Фернандо Леон Де Араноа",
        "genre": "комедия,драма,военный",
        "actors": "Бенисио Дель Торо, Тим Роббинс, Ольга Куриленко, Мелани Тьерри, Федя Стукан, Eldar Residovic, Серхи Лопес, Ненад Вукелич, Мортен Суурбалле, Бен Темпле",
        "description": "Группа сотрудников гуманитарной службы пытается достать труп из колодца в зоне конфликта. Кто-то бросил туда тело, чтобы отравить воду, и местные люди мучаются от жажды. Задача, которая кажется простейшей, превращается в невыполнимую миссию, в которой злейший враг - иррациональность. Работники пересекают местность, охваченную войной, пытаясь решить эту проблему.",
        "slogan": "",
        "premiere": "16 мая 2015",
        "age": "0",
        "time": "6360",
        "poster": "https://st.kp.yandex.net/images/film_iphone/iphone360_838222.jpg",
        "rating": {
          "rating_kp": "6.612",
          "vote_num_kp": "3018",
          "rating_imdb": "6.8",
          "vote_num_imdb": "21439"
        }
      }
    },
    {
      "link": "",
      "kinopoisk_id": "1198735",
      "date": "1633248131",
      "camrip": "0",
      "ads": "0",
      "block": "",
      "serial": "0",
      "end": "0",
      "quality": "WEB-DLRip",
      "translation": "Оригинал",
      "max_qual": "1080",
      "info": {
        "rus": "Нефутбол",
        "orig": "Нефутбол",
        "alter": "",
        "year": "2021",
        "country": "Россия",
        "director": "Максим Свешников",
        "genre": "комедия,спорт",
        "actors": "Любовь Аксенова,Егор Корешков,Юлия Топольницкая,Алина Алексеева,Александра Кузенкина,Полина Ауг,Мария Ивакова,Валентина Ляпина,Зарина Мухитдинова,Роман Мадянов",
        "description": "Дане Белых с детства твердили, что футбол — не женское дело, но она все равно стала капитаном футбольной команды. Вот только ее команду неожиданно собрались закрывать. Спасти их может только победа. И Даня решает собрать своих подруг детства, с которыми играла в футбол еще в школе. Это оказывается не так-то просто, а тут еще и тренер — бывшая «звезда» с проблемами, который вообще не считает женский футбол футболом… Но отправив на скамейку запасных неуверенность в себе, лишний вес и проблемы на личном фронте, девчонки рвутся к победе не только в спорте, но и в жизни.",
        "slogan": "",
        "premiere": "1 сентября 2021",
        "age": "12",
        "time": "5400",
        "poster": "https://st.kp.yandex.net/images/film_iphone/iphone360_1198735.jpg",
        "rating": {
          "rating_kp": "6.042",
          "vote_num_kp": "1985",
          "rating_imdb": 0,
          "vote_num_imdb": 0
        }
      }
    },
    {
      "link": "",
      "kinopoisk_id": "4536610",
      "date": "1633236612",
      "camrip": "0",
      "ads": "1",
      "block": "",
      "serial": "0",
      "end": "0",
      "quality": "WEB-DLRip",
      "translation": "Многоголосый",
      "max_qual": "1080",
      "info": {
        "rus": "Вечно богатый",
        "orig": "Forever Rich",
        "alter": "",
        "year": "2021",
        "country": "Нидерланды",
        "director": "Шады Эль-Хамус",
        "genre": "триллер,драма,комедия,криминал",
        "actors": "Юта Вонг Лой Синг,Хадевих Минис,Йонас Смулдерс,Маттео ван дер Грийн,Sinem Kavus,Мустафа Дюгулу,Sergio Fontana,Daniël Kolf,Simon van Lammeren,Зои Лав Смит",
        "description": "Восходящая суперзвезда рэпа выходит из себя, когда унизительное видео становится вирусным и толкает его на битву за искупление в течение одной долгой ночи.",
        "slogan": "Netflix",
        "premiere": "1 октября 2021",
        "age": "0",
        "time": "5340",
        "poster": "https://m.media-amazon.com/images/M/MV5BNTRkOGMxYzgtMThkYy00OTk4LWJlYjQtNTg5ZjNlZWQyYmJjXkEyXkFqcGdeQXVyMTI0NzM3Nzg1.jpg",
        "rating": {
          "rating_kp": "0",
          "vote_num_kp": "30",
          "rating_imdb": "5.5",
          "vote_num_imdb": "547"
        }
      }
    },
    {
      "link": "",
      "kinopoisk_id": "1313395",
      "date": "1633231836",
      "camrip": "0",
      "ads": "1",
      "block": "",
      "serial": "0",
      "end": "0",
      "quality": "WEB-DLRip",
      "translation": "Многоголосый",
      "max_qual": "1080",
      "info": {
        "rus": "Семейка Аддамс: Горящий тур",
        "orig": "The Addams Family 2",
        "alter": "",
        "year": "2021",
        "country": "Великобритания,Канада,США",
        "director": "Грег Тирнан,Конрад Вернон",
        "genre": "мультфильм,ужасы,фэнтези,комедия,приключения,семейный",
        "actors": "Оскар Айзек,Шарлиз Терон,Хлоя Грейс Морец,Ник Кролл,Джейвон Уолтон,Снуп Догг,Бетт Мидлер,Билл Хейдер,Уоллес Шоун",
        "description": "Что делать, если в доме поселилось настоящее исчадие ада, а именно два подростка? Срочно планировать самый жуткий отпуск! Мартиша, Гомес, Уэнсдей, Пагсли и дядя Фестер загружаются в семейный походный катафалк, чтобы отправиться навстречу новым приключениям и чудаковатым друзьям, от которых волосы встанут дыбом. В этой поездке семейка Аддамс сплотится намертво! Если, конечно, останутся выжившие…",
        "slogan": "Снова не рады видеть вас",
        "premiere": "14 октября 2021",
        "age": "12",
        "time": "5580",
        "poster": "https://st.kp.yandex.net/images/film_iphone/iphone360_1313395.jpg",
        "rating": {
          "rating_kp": "5.496",
          "vote_num_kp": "1889",
          "rating_imdb": "5.3",
          "vote_num_imdb": "2880"
        }
      }
    },
    {
      "link": "",
      "kinopoisk_id": "1157786",
      "date": "1633230612",
      "camrip": "0",
      "ads": "1",
      "block": "",
      "serial": "0",
      "end": "0",
      "quality": "WEB-DLRip",
      "translation": "Многоголосый",
      "max_qual": "1080",
      "info": {
        "rus": "Превратности разума",
        "orig": "Adventures of a Mathematician",
        "alter": "",
        "year": "2020",
        "country": "Германия,Польша,Великобритания",
        "director": "Торстен Клайн",
        "genre": "драма,биография",
        "actors": "Филип Тлокински,Эстер Гаррель,Сэм Кили,Йоэль Басман,Fabian Kociecki,Райан Гейдж,Сабин Тамбреа,Матеуш Вецлавек,Джеймс Собол Келли,Альберто Руано",
        "description": "История польского математика Станислава Улама, переехавшего в США в 1930-х годах.",
        "slogan": "",
        "premiere": "28 октября 2021",
        "age": "12",
        "time": "6120",
        "poster": "https://st.kp.yandex.net/images/film_iphone/iphone360_1157786.jpg",
        "rating": {
          "rating_kp": "0",
          "vote_num_kp": "19",
          "rating_imdb": "5.5",
          "vote_num_imdb": "150"
        }
      }
    },
    {
      "link": "",
      "kinopoisk_id": "1038364",
      "date": "1633211405",
      "camrip": "0",
      "ads": "1",
      "block": "",
      "serial": "0",
      "end": "0",
      "quality": "WEB-DLRip",
      "translation": "Многоголосый",
      "max_qual": "720",
      "info": {
        "rus": "Форментера Леди",
        "orig": "Formentera Lady",
        "alter": "",
        "year": "2018",
        "country": "Испания",
        "director": "Пау Дура",
        "genre": "драма,комедия",
        "actors": "Хосе Сакристан,Sandro Ballesteros,Хорди Санчес,Нора Навас,Ферран Ранье,Пепа Хуан,Нурия Менсия,Мирейа Рос,Хули Мира,Хулио Канто",
        "description": "Бывший хиппи и поклонник свободной жизни Сэмюэл прекрасно себя чувствовал проживая на отдаленном острове в небольшой хижине без особенных удобств. Периодически он играл в местном баре на банджо, стараясь создать хорошее настроение старинным друзьям. Но большую часть времени аскет проводил в одиночестве, предаваясь воспоминаниям о веселом прошлом. Приезд дочери стал настоящей неожиданностью для старика, который не виделся с ней долгое время и не собирался ничего менять в данном вопросе. Анна планировала скорый отъезд из-за работы во Францию, поэтому искала место временного проживания для сына. Марк не демонстрировал особенной радости от встречи с родственником о существовании которого ничего не знал. Строгий дедушка тоже не горел желанием менять образ жизни ради внука, но права выбора не оказалось у них обоих. Представителям разных поколений предстояло научиться совместному проживанию на общей территории, до возвращения из командировки Анны. Правда сколько времени займет этот процесс и к каким последствиям приведет в ближайшем будущем, они не осознавали.",
        "slogan": "",
        "premiere": "16 апреля 2018",
        "age": "0",
        "time": "5100",
        "poster": "https://st.kp.yandex.net/images/film_iphone/iphone360_1038364.jpg",
        "rating": {
          "rating_kp": "0",
          "vote_num_kp": "6",
          "rating_imdb": "5.6",
          "vote_num_imdb": "157"
        }
      }
    },
    {
      "link": "",
      "kinopoisk_id": "1313857",
      "date": "1633210811",
      "camrip": "0",
      "ads": "1",
      "block": "",
      "serial": "0",
      "end": "0",
      "quality": "WEB-DLRip",
      "translation": "Многоголосый",
      "max_qual": "720",
      "info": {
        "rus": "Ховард Ориджинал",
        "orig": "Howard Original",
        "alter": "",
        "year": "2020",
        "country": "США",
        "director": "Natalie Rodriguez",
        "genre": "драма,комедия",
        "actors": "Эмбер Полин Магдесян,Ивон Миллан,Кевин Шон Майклс,Iliyana Apostolova,Katt Balsan,Natasha Galano,Алессандра Мэнон,Merlyn Scoggin,Jasmine Richards,Alexandra Almendarez",
        "description": "Комедийно-драматическая сатира о шоу-бизнесе, где сценарист-неудачник сталкивается с множеством жизненных передряг, а его любимая кошка оживает. По мотивам короткометражного фильма «Ховард» 2017 года.",
        "slogan": "",
        "premiere": "13 ноября 2020",
        "age": "0",
        "time": "5640",
        "poster": "https://m.media-amazon.com/images/M/MV5BZGFiZGVjZWYtY2MwNy00ZmU0LWJjMTAtZGJjNjNhZjkwOWE0XkEyXkFqcGdeQXVyNTE0NDA5NTU@.jpg",
        "rating": {
          "rating_kp": "0",
          "vote_num_kp": "1",
          "rating_imdb": "4.6",
          "vote_num_imdb": "59"
        }
      }
    },
    {
      "link": "",
      "kinopoisk_id": "4396134",
      "date": "1633207333",
      "camrip": "0",
      "ads": "0",
      "block": "",
      "serial": "1",
      "end": "0",
      "quality": "WEB-DLRip",
      "translation": "StudioBand",
      "max_qual": "1080",
      "last_season": "1",
      "last_episode": "12",
      "episodes": {
        "1": {
          "1": 1080,
          "2": 1080,
          "3": 1080,
          "4": 1080,
          "5": 1080,
          "6": 1080,
          "7": 1080,
          "8": 1080,
          "9": 1080,
          "10": 1080,
          "11": 1080,
          "12": 1080
        }
      },
      "info": {
        "rus": "Ре-Мейн",
        "orig": "Re-Main",
        "alter": "",
        "year": "2021",
        "country": "Япония",
        "director": "Киёси Мацуда",
        "genre": "мультфильм,драма,спорт",
        "actors": "Субару Кимура,Котаро Нисияма,Юто Уэмура",
        "description": "Возвращаясь с победы на зимнем чемпионате Японии по водному поло, девятиклассник Минато Киёмидзу попадает в аварию и впадает в кому. Спустя 203 дня он наконец пробуждается, лишённый памяти о девятом классе. Чтобы сменить обстановку и оставить спорт в прошлом, Минато переводится в старшую школу Яманами. Но обещание заставляет его опять заняться водным поло вместе с новыми друзьями. Однако на пути новоиспечённого кружка стоит немало преград...",
        "slogan": "",
        "premiere": "",
        "age": "0",
        "time": "1500",
        "poster": "https://m.media-amazon.com/images/M/MV5BMWI2NWIzMzQtMThmYi00NTk4LThhODgtNTc2NDU2MTkzN2I2XkEyXkFqcGdeQXVyNDYzNDg2MTM@.jpg",
        "rating": {
          "rating_kp": "0",
          "vote_num_kp": "52",
          "rating_imdb": "7.3",
          "vote_num_imdb": "168"
        }
      }
    },
    {
      "link": "",
      "kinopoisk_id": "1273018",
      "date": "1633200605",
      "camrip": "0",
      "ads": "1",
      "block": "",
      "serial": "0",
      "end": "0",
      "quality": "BDRip",
      "translation": "Многоголосый",
      "max_qual": "1080",
      "info": {
        "rus": "Мистериум: Эффект Марко",
        "orig": "Marco effekten",
        "alter": "",
        "year": "2021",
        "country": "Дания,Германия",
        "director": "Мартин Зандвлиет",
        "genre": "триллер,криминал",
        "actors": "Ульрих Томсен,Заки Юссеф,Софи Торп,Андерс Маттесен,Lobus Olàh,Хенрик Ноэль Олесен,Томас В. Габриэльссон,Лиза Карлехед,Каспар Филлипсон,Louise Gammelgaard",
        "description": "Его зовут Марко, и он — член преступного клана. Марко мечтает лишь об одном — сбежать и зажить нормальной жизнью. Однажды он узнает о страшном убийстве, за это клан приговаривает его к смерти. Единственный шанс на спасение — начальник отдела полиции Карл Мерк, храбрый и неподкупный одиночка.",
        "slogan": "Чужой среди своих",
        "premiere": "14 октября 2021",
        "age": "18",
        "time": "7200",
        "poster": "https://st.kp.yandex.net/images/film_iphone/iphone360_1273018.jpg",
        "rating": {
          "rating_kp": "0",
          "vote_num_kp": "97",
          "rating_imdb": "5.1",
          "vote_num_imdb": "758"
        }
      }
    },
    {
      "link": "",
      "kinopoisk_id": "4633073",
      "date": "1633197609",
      "camrip": "0",
      "ads": "1",
      "block": "",
      "serial": "0",
      "end": "0",
      "quality": "WEB-DLRip",
      "translation": "Многоголосый",
      "max_qual": "720",
      "info": {
        "rus": "Закапывая прошлое",
        "orig": "Bury the Past",
        "alter": "",
        "year": "2021",
        "country": "Канада",
        "director": "Макс МакГуайр",
        "genre": "триллер",
        "actors": "Сара Аллен,Ребекка Амзаллак,Tomas Chovanec,Stephanie Herrera,М. Джон Кеннеди,Дэймон Рунян,Мэтт Уэллс",
        "description": "Защищаясь от своего мужа-тирана, Лиз случайно его убивает, после чего сбегает с места преступления и обретает спокойную жизнь под другим именем и с другим мужем. Однако призраки прошлого настигают её, и семейному счастью приходит конец.",
        "slogan": "",
        "premiere": "10 сентября 2021",
        "age": "0",
        "time": "5400",
        "poster": "https://m.media-amazon.com/images/M/MV5BNjBkZTgzOTctMzk1OS00NjNlLThhYzctMDkxNmNkZmU4N2M2XkEyXkFqcGdeQXVyODk2MzQ0OTc@.jpg",
        "rating": {
          "rating_kp": "0",
          "vote_num_kp": "4",
          "rating_imdb": "5.6",
          "vote_num_imdb": "45"
        }
      }
    },
    {
      "link": "",
      "kinopoisk_id": "1020660",
      "date": "1633186214",
      "camrip": "0",
      "ads": "0",
      "block": "",
      "serial": "0",
      "end": "0",
      "quality": "BDRip",
      "translation": "Многоголосый",
      "max_qual": "1080",
      "info": {
        "rus": "Чёрная нить",
        "orig": "The Black String",
        "alter": "",
        "year": "2018",
        "country": "США",
        "director": "Брайан Хэнсон",
        "genre": "ужасы,драма,детектив",
        "actors": "Фрэнки Муниз,Блейк Уэбб,Челси Эдмундсон,Ричард Хэндли,Каллен Дуглас,Колби Френч,Лаура Ричардсон,Рави Патель,Mary K. DeVault,Джеки Мур",
        "description": "Кроме работы продавцом в магазине неудачник Джонатан ничем особенным не занят. Однажды он звонит на номер из рекламы, обещающей приятные знакомства, и проводит ночь с незнакомкой Диной. На следующий день Джонатан обнаруживает у себя странную сыпь, замечает повсюду подозрительного типа в шляпе, а также выясняет, что про Дину никто слыхом не слыхивал. Парень решает, что его прокляли.",
        "slogan": "When Nightmares Become Reality",
        "premiere": "25 октября 2018",
        "age": "18",
        "time": "5580",
        "poster": "https://st.kp.yandex.net/images/film_iphone/iphone360_1020660.jpg",
        "rating": {
          "rating_kp": "5.306",
          "vote_num_kp": "164",
          "rating_imdb": "5.3",
          "vote_num_imdb": "1096"
        }
      }
    }
  ]
}
